pragma/__init__.py
pragma/collapse_literals.py
pragma/deindex.py
pragma/inline.py
pragma/lift.py
pragma/unroll.py
pragma/core/__init__.py
pragma/core/stack.py
pragma/core/transformer.py
pragma/core/resolve/__init__.py
pragma/core/resolve/indexable.py
pragma/core/resolve/iterable.py
pragma/core/resolve/literal.py
pragma-0.2.4.dist-info/LICENSE
pragma-0.2.4.dist-info/METADATA
pragma-0.2.4.dist-info/WHEEL
pragma-0.2.4.dist-info/top_level.txt
pragma-0.2.4.dist-info/RECORD
