Metadata-Version: 2.1
Name: pragma
Version: 0.2.4
Summary: Python code transformers that mimic pragma compiler directives
Home-page: https://github.com/scnerd/pypragma
Author: scnerd
Author-email: scnerd@gmail.com
License: MIT
Platform: UNKNOWN
Requires-Dist: miniutils
Requires-Dist: astor
